{
  "name": "linkedin_connection_Mian_Haroon_8e0a6b9661c5.md",
  "size": 1886,
  "timestamp": "2026-02-23T22:06:57.575741+00:00",
  "status": "complete",
  "type": "linkedin",
  "category": "feature",
  "actor": "Mian Haroon",
  "matched_keywords": [
    "posted"
  ],
  "analyzed_at": "2026-02-23T22:12:52.429702+00:00",
  "sensitive": true,
  "plan": "plans/Plan_linkedin_connection_Mian_Haroon_8e0a6b9661c5_md.md",
  "analysis": {
    "word_count": 213,
    "line_count": 15,
    "char_count": 1492,
    "key_phrases": [
      "# LinkedIn Notification \u2014 Connection",
      "- **From:** Mian Haroon",
      "- **Category:** connection",
      "- **Notification time:** 11h",
      "- **Captured:** 2026-02-23T22:06:57.574990+00:00"
    ],
    "category": "feature"
  }
}